setup.py
facade/__init__.py
facade/base.py
facade/dll.py
facade/ini.py
facade/js.py
facade/json.py
facade/pyv.py
facade/yaml.py
facade.egg-info/PKG-INFO
facade.egg-info/SOURCES.txt
facade.egg-info/dependency_links.txt
facade.egg-info/top_level.txt