Metadata-Version: 1.0
Name: facade
Version: 0.1.5
Summary: Meta loaders for fun and profit
Home-page: http://github.com/oakfang/facade
Author: Alon Niv
Author-email: oakfang@gmail.com
License: MIT
Platform: UNKNOWN
